datavision_beeyard_sdk/__init__.py
datavision_beeyard_sdk/api/__init__.py
datavision_beeyard_sdk/api/cell/__init__.py
datavision_beeyard_sdk/api/cell/add_properties.py
datavision_beeyard_sdk/api/cell/add_references.py
datavision_beeyard_sdk/api/cell/add_tags.py
datavision_beeyard_sdk/api/cell/aggregate_cells.py
datavision_beeyard_sdk/api/cell/create_cell.py
datavision_beeyard_sdk/api/cell/list_referenced_cells.py
datavision_beeyard_sdk/api/cell/modify_cell_description.py
datavision_beeyard_sdk/api/cell/modify_property.py
datavision_beeyard_sdk/api/cell/read_cell.py
datavision_beeyard_sdk/api/cell/remove_cell.py
datavision_beeyard_sdk/api/cell/remove_properties.py
datavision_beeyard_sdk/api/cell/remove_references.py
datavision_beeyard_sdk/api/cell/remove_tags.py
datavision_beeyard_sdk/api/cell/search_cells.py
datavision_beeyard_sdk/api/cell/update_tags.py
datavision_beeyard_sdk/api/cell/upload_cell.py
datavision_beeyard_sdk/api/document/__init__.py
datavision_beeyard_sdk/api/document/add_documents.py
datavision_beeyard_sdk/api/document/modify_document.py
datavision_beeyard_sdk/api/event/__init__.py
datavision_beeyard_sdk/api/event/aggregate_events.py
datavision_beeyard_sdk/api/event/read_event.py
datavision_beeyard_sdk/api/event/search_events.py
datavision_beeyard_sdk/api/file/__init__.py
datavision_beeyard_sdk/api/file/add_files.py
datavision_beeyard_sdk/api/file/add_properties.py
datavision_beeyard_sdk/api/file/modify_file.py
datavision_beeyard_sdk/api/file/modify_property.py
datavision_beeyard_sdk/api/file/read_file.py
datavision_beeyard_sdk/api/file/remove_files.py
datavision_beeyard_sdk/api/file/remove_properties.py
datavision_beeyard_sdk/api/file/update_tags.py
datavision_beeyard_sdk/api/health/__init__.py
datavision_beeyard_sdk/api/health/get_liveness.py
datavision_beeyard_sdk/api/health/get_readiness.py
datavision_beeyard_sdk/api/image/__init__.py
datavision_beeyard_sdk/api/image/add_images.py
datavision_beeyard_sdk/api/image/create_image_thumbnail.py
datavision_beeyard_sdk-12.6.0.dist-info/METADATA
datavision_beeyard_sdk-12.6.0.dist-info/WHEEL
datavision_beeyard_sdk-12.6.0.dist-info/RECORD
