Metadata-Version: 2.1
Name: datavision-beeyard-sdk
Version: 12.6.0
Summary: BeeYard Python SDK
Home-page: https://docs.beeyard.ai/docs/reference/sdk/python/
License: MIT
Keywords: python,sdk,beeyard
Author: DataVision
Author-email: support@datavision.software
Requires-Python: >=3.8,<4.0
Classifier: License :: OSI Approved :: MIT License
Classifier: Operating System :: OS Independent
Classifier: Programming Language :: Python :: 3
Classifier: Programming Language :: Python :: 3.8
Classifier: Programming Language :: Python :: 3.9
Classifier: Programming Language :: Python :: 3.10
Classifier: Programming Language :: Python :: 3.11
Classifier: Topic :: Software Development :: Libraries :: Python Modules
Requires-Dist: attrs (>=21.2.0,<22.0.0)
Requires-Dist: httpx (>=0.24.1,<0.25.0)
